[{"ID":30,"title":"moireShader","image":"30.png","date":2020.3,"url":"works/30_moireShader/index.html"},{"ID":29,"title":"particleCircle","image":"29.png","date":2020.3,"url":"works/29_particleCircle/index.html"},{"ID":28,"title":"rainfall","image":"28.png","date":2020.2,"url":"works/28_rainfall/index.html"},{"ID":27,"title":"neonWave","image":"27.png","date":2020.1,"url":"works/27_neonWave/index.html"},{"ID":26,"title":"spiralParticle","image":"26.png","date":2020.1,"url":"works/26_spiralParticle/index.html"},{"ID":25,"title":"Noise","image":"25.png","date":2020.1,"url":"works/25_Noise/index.html"},{"ID":24,"title":"KAGAMI MOCHI","image":"24.png","date":2020.1,"url":"works/24_KAGAMI MOCHI/index.html"},{"ID":23,"title":"colorfulShader","image":"23.png","date":2019.12,"url":"works/23_colorfulShader/index.html"},{"ID":22,"title":"noiseWave","image":"22.png","date":2019.11,"url":"works/22_noiseWave/index.html"},{"ID":21,"title":"skybox","image":"21.png","date":"2019.10","url":"works/21_skybox/index.html"},{"ID":20,"title":"fractalLine","image":"20.png","date":"2019.10","url":"works/20_fractalLine/index.html"},{"ID":19,"title":"lineWave","image":"19.png","date":2019.8,"url":"works/19_lineWave/index.html"},{"ID":18,"title":"soundVisualize2","image":"18.png","date":2019.7,"url":"works/18_soundVisualize2/index.html"},{"ID":17,"title":"ruledSurface","image":"17.png","date":2019.7,"url":"works/17_ruledSurface/index.html"},{"ID":16,"title":"Galaxy","image":"16.png","date":2019.6,"url":"works/16_Galaxy/index.html"},{"ID":15,"title":"neonLine","image":"15.png","date":2019.6,"url":"works/15_neonLine/index.html"},{"ID":14,"title":"GlitchEffect","image":"14.png","date":2019.6,"url":"works/14_GlitchEffect/index.html"},{"ID":13,"title":"ColorParticleHelix","image":"13.png","date":2019.5,"url":"works/13_ColorParticleHelix/index.html"},{"ID":12,"title":"sincosPattern","image":"12.png","date":2019.5,"url":"works/12_sincosPattern/index.html"},{"ID":11,"title":"bubbleRing","image":"11.png","date":2019.4,"url":"works/11_bubbleRing/index.html"},{"ID":10,"title":"mojibake","image":"10.png","date":2019.3,"url":"works/10_mojibake/index.html"},{"ID":9,"title":"soundVisualize","image":"9.png","date":2019.2,"url":"works/09_soundVisualize/index.html"},{"ID":8,"title":"cubePattern","image":"8.png","date":2019.1,"url":"works/08_cubePattern/index.html"},{"ID":7,"title":"snowfall","image":"7.png","date":2018.12,"url":"works/07_snowfall/index.html"},{"ID":6,"title":"emitRectangle","image":"6.png","date":2018.11,"url":"works/06_emitRectangle/index.html"},{"ID":5,"title":"bubbleParticle","image":"5.png","date":2018.11,"url":"works/05_bubbleParticle/index.html"},{"ID":4,"title":"favorite","image":"4.png","date":2018.11,"url":"works/04_favorite/index.html"},{"ID":3,"title":"MoireGenerator","image":"3.png","date":2017,"url":"works/03_MoireGenerator/index.html"},{"ID":2,"title":"UrokoPattern","image":"2.png","date":2017,"url":"works/02_UrokoPattern/index.html"},{"ID":1,"title":"firefly","image":"1.png","date":2017,"url":"works/01_firefly/index.html"}]